reservauto/__init__.py
reservauto/client.py
reservauto-0.1.5.dist-info/METADATA
reservauto-0.1.5.dist-info/WHEEL
reservauto-0.1.5.dist-info/RECORD
