Metadata-Version: 2.1
Name: reservauto
Version: 0.1.5
Summary: Unofficial Python package for Reservauto's API
License: MIT
Author: FloDevelops
Author-email: 65234487+FloDevelops@users.noreply.github.com
Requires-Python: >=3.11,<4.0
Classifier: License :: OSI Approved :: MIT License
Classifier: Programming Language :: Python :: 3
Classifier: Programming Language :: Python :: 3.11
Requires-Dist: requests (>=2.31.0,<3.0.0)
